netbox_animal_sounds/__init__.py
netbox_animal_sounds/admin.py
netbox_animal_sounds/models.py
netbox_animal_sounds/navigation.py
netbox_animal_sounds/template_content.py
netbox_animal_sounds/urls.py
netbox_animal_sounds/views.py
netbox_animal_sounds/api/serializers.py
netbox_animal_sounds/api/urls.py
netbox_animal_sounds/api/views.py
netbox_animal_sounds/migrations/0001_initial.py
netbox_animal_sounds/migrations/__init__.py
netbox_animal_sounds/templates/netbox_animal_sounds/animal.html
netbox_animal_sounds/templates/netbox_animal_sounds/animal_list.html
netbox_animal_sounds/templates/netbox_animal_sounds/inc/animal_count.html
netbox_animal_sounds_test-0.0.8.dist-info/LICENCE
netbox_animal_sounds_test-0.0.8.dist-info/METADATA
netbox_animal_sounds_test-0.0.8.dist-info/WHEEL
netbox_animal_sounds_test-0.0.8.dist-info/top_level.txt
netbox_animal_sounds_test-0.0.8.dist-info/RECORD
