Metadata-Version: 2.1
Name: netbox-animal-sounds-test
Version: 0.0.8
Summary: An example NetBox plugin
Home-page: https://github.com/netbox-community/netbox-animal-sounds
Author: Jeremy Stretch
Author-email: UNKNOWN
License: Apache 2.0
Platform: UNKNOWN
